Workbook

Sheet Методология
A1: Методология расчёта статей P&L
A3: Статья | B3: База расчёта | C3: Источник
A4: Чистая выручка | B4: Валовая выручка − Возвраты по этой строке | C4: Источники (G = E − F)
A5: Себестоимость | B5: qty проданных (только refund=N) × средневзвешенная ₽/шт по SKU | C5: 1c-production.xlsx → Σ(qty × cost_pu)/Σ(qty)
A6: Комиссия | B6: Чистая выручка строки × Комиссия % канала | C6: tariffs.xlsx → Комиссия, %
A7: Логистика | B7: qty (только refund=N) × Логистика ₽/шт канала | C7: tariffs.xlsx → Логистика, ₽/шт
A8: Эквайринг | B8: Включён в комиссию маркетплейса (отдельно не выделяется) | C8: —
A9: ДРР (реклама) | B9: Валовая выручка строки × ДРР % канала. ВАЖНО: база — валовая, не чистая | C9: tariffs.xlsx → ДРР, %
A10: Соинвест Озон | B10: Чистая выручка Озон-строки × % периода по SKU. Знак qty учитывается: refund=Y → соинвест сторнируется (отрицательный). WB соинвеста нет. | C10: ozon-coinvest.xlsx → % баллов по периоду и SKU
A11: Маржинальная прибыль | B11: Валовая прибыль − Комиссия − Логистика − Эквайринг − ДРР + Соинвест (см. формулу на листе «Маржинальная») | C11: Маржинальная (J = D − E − F − G − H + I)
A12: Постоянные | B12: Σ 5 статей opex (ФОТ, Аренда, IT, Прочие услуги, Прочие административные). Аллокация по категориям пропорционально доле выручки. | C12: opex.xlsx
A13: Бренд-маркетинг | B13: Пул бренд-рекламы (отдельная строка ниже маржинальной). Аллокация по категориям пропорционально доле выручки. | C13: opex.xlsx → Бренд-реклама
A14: Транспорт завод→FBO | B14: Пул транспортных расходов (отдельная строка ниже маржинальной). Аллокация по категориям пропорционально доле выручки. | C14: opex.xlsx → Транспорт завод→FBO
A15: EBITDA | B15: Маржинальная − Постоянные − Бренд − Транспорт (по категориям и в сумме) | C15: Операционная (H = C − E − F − G)

Sheet Источники
A1: SKU | B1: Канал | C1: Категория | D1: Объём | E1: Выручка валовая, ₽ | F1: Возврат, ₽ | G1: Чистая выручка, ₽ | H1: Себестоимость, ₽ | I1: Комиссия, ₽ | J1: Логистика, ₽ | K1: Эквайринг (в комиссии), ₽ | L1: ДРР, ₽ | M1: Соинвест, ₽
A2: ABC-CLN-042 | B2: Ozon | C2: Бытхимия | D2: 15580 | E2: 5620827.8 | F2: 333910.56 | G2: 5286917.2 | H2: 1733621.8 | I2: 1427467.6 | J2: 545300 | K2: 0 | L2: 333910.56 | M2: 107500.65
A3: ABC-CLN-042 | B3: WB | C3: Бытхимия | D3: 9840 | E3: 3602219 | F3: 222762.84 | G3: 3379456.2 | H3: 1094919 | I3: 996939.57 | J3: 464940 | K3: 0 | L3: 210890.88 | M3: 0
A4: ABC-LDR-034 | B4: Ozon | C4: Бытхимия | D4: 5330 | E4: 3698118 | F4: 263052.72 | G4: 3435065.3 | H4: 1182884.9 | I4: 927467.63 | J4: 319800 | K4: 0 | L4: 214138.08 | M4: 34350.65
A5: ABC-LDR-034 | B5: WB | C5: Бытхимия | D5: 3526 | E5: 2474228.6 | F5: 168150.84 | G5: 2306077.8 | H5: 782523.88 | I5: 680292.95 | J5: 285606 | K5: 0 | L5: 141660.74 | M5: 0
A6: ABC-LDR-027 | B6: Ozon | C6: Бытхимия | D6: 7052 | E6: 2004416.2 | F6: 102254 | G6: 1902162.2 | H6: 749343.5 | I6: 513583.79 | J6: 282080 | K6: 0 | L6: 116569.56 | M6: 34872.98
A7: ABC-LDR-027 | B7: WB | C7: Бытхимия | D7: 4428 | E7: 1249163.4 | F7: 62303.6 | G7: 1186859.8 | H7: 470518.02 | I7: 350123.64 | J7: 239112 | K7: 0 | L7: 73194.84 | M7: 0
A8: ABC-DSH-018 | B8: Ozon | C8: Посуда | D8: 12300 | E8: 2880463.2 | F8: 147600 | G8: 2732863.2 | H8: 929077.5 | I8: 737873.06 | J8: 307500 | K8: 0 | L8: 168264 | M8: 27328.63
A9: ABC-DSH-018 | B9: WB | C9: Посуда | D9: 7872 | E9: 1804094.3 | F9: 89084.8 | G9: 1715009.5 | H9: 594609.6 | I9: 505927.81 | J9: 265680 | K9: 0 | L9: 107688.96 | M9: 0
A10: ABC-KIT-051 | B10: Ozon | C10: Посуда | D10: 5740 | E10: 1960353.5 | F10: 137817.4 | G10: 1822536.1 | H10: 640860.3 | I10: 492084.75 | J10: 200900 | K10: 0 | L10: 112102.2 | M10: 39488.28
A11: ABC-KIT-051 | B11: WB | C11: Посуда | D11: 3936 | E11: 1339716 | F11: 92299.2 | G11: 1247416.8 | H11: 439447.06 | I11: 367987.96 | J11: 185976 | K11: 0 | L11: 76870.08 | M11: 0
A12: ABC-WND-009 | B12: Ozon | C12: Стёкла | D12: 7954 | E12: 1662368 | F12: 136490.64 | G12: 1525877.3 | H12: 610997.13 | I12: 411986.88 | J12: 278390 | K12: 0 | L12: 96593.54 | M12: 122070.19
A13: ABC-WND-009 | B13: WB | C13: Стёкла | D13: 5248 | E13: 1128789 | F13: 92364.8 | G13: 1036424.2 | H13: 403132.13 | I13: 305745.15 | J13: 247968 | K13: 0 | L13: 63732.04 | M13: 0

Sheet Валовая
A1: SKU | B1: Канал | C1: Категория | D1: Чистая выручка, ₽ | E1: Себестоимость, ₽ | F1: Валовая прибыль, ₽
A2: =Источники!A2 | B2: =Источники!B2 | C2: =Источники!C2 | D2: =Источники!G2 | E2: =Источники!H2 | F2: =D2-E2
A3: =Источники!A3 | B3: =Источники!B3 | C3: =Источники!C3 | D3: =Источники!G3 | E3: =Источники!H3 | F3: =D3-E3
A4: =Источники!A4 | B4: =Источники!B4 | C4: =Источники!C4 | D4: =Источники!G4 | E4: =Источники!H4 | F4: =D4-E4
A5: =Источники!A5 | B5: =Источники!B5 | C5: =Источники!C5 | D5: =Источники!G5 | E5: =Источники!H5 | F5: =D5-E5
A6: =Источники!A6 | B6: =Источники!B6 | C6: =Источники!C6 | D6: =Источники!G6 | E6: =Источники!H6 | F6: =D6-E6
A7: =Источники!A7 | B7: =Источники!B7 | C7: =Источники!C7 | D7: =Источники!G7 | E7: =Источники!H7 | F7: =D7-E7
A8: =Источники!A8 | B8: =Источники!B8 | C8: =Источники!C8 | D8: =Источники!G8 | E8: =Источники!H8 | F8: =D8-E8
A9: =Источники!A9 | B9: =Источники!B9 | C9: =Источники!C9 | D9: =Источники!G9 | E9: =Источники!H9 | F9: =D9-E9
A10: =Источники!A10 | B10: =Источники!B10 | C10: =Источники!C10 | D10: =Источники!G10 | E10: =Источники!H10 | F10: =D10-E10
A11: =Источники!A11 | B11: =Источники!B11 | C11: =Источники!C11 | D11: =Источники!G11 | E11: =Источники!H11 | F11: =D11-E11
A12: =Источники!A12 | B12: =Источники!B12 | C12: =Источники!C12 | D12: =Источники!G12 | E12: =Источники!H12 | F12: =D12-E12
A13: =Источники!A13 | B13: =Источники!B13 | C13: =Источники!C13 | D13: =Источники!G13 | E13: =Источники!H13 | F13: =D13-E13

Sheet Маржинальная
A1: SKU | B1: Канал | C1: Категория | D1: Валовая прибыль, ₽ | E1: Комиссия, ₽ | F1: Логистика, ₽ | G1: Эквайринг, ₽ | H1: ДРР, ₽ | I1: Соинвест, ₽ | J1: Маржинальная прибыль, ₽
A2: =Валовая!A2 | B2: =Валовая!B2 | C2: =Валовая!C2 | D2: =Валовая!F2 | E2: =Источники!I2 | F2: =Источники!J2 | G2: =Источники!K2 | H2: =Источники!L2 | I2: =Источники!M2 | J2: =D2-E2-F2-G2-H2+I2
A3: =Валовая!A3 | B3: =Валовая!B3 | C3: =Валовая!C3 | D3: =Валовая!F3 | E3: =Источники!I3 | F3: =Источники!J3 | G3: =Источники!K3 | H3: =Источники!L3 | I3: =Источники!M3 | J3: =D3-E3-F3-G3-H3+I3
A4: =Валовая!A4 | B4: =Валовая!B4 | C4: =Валовая!C4 | D4: =Валовая!F4 | E4: =Источники!I4 | F4: =Источники!J4 | G4: =Источники!K4 | H4: =Источники!L4 | I4: =Источники!M4 | J4: =D4-E4-F4-G4-H4+I4
A5: =Валовая!A5 | B5: =Валовая!B5 | C5: =Валовая!C5 | D5: =Валовая!F5 | E5: =Источники!I5 | F5: =Источники!J5 | G5: =Источники!K5 | H5: =Источники!L5 | I5: =Источники!M5 | J5: =D5-E5-F5-G5-H5+I5
A6: =Валовая!A6 | B6: =Валовая!B6 | C6: =Валовая!C6 | D6: =Валовая!F6 | E6: =Источники!I6 | F6: =Источники!J6 | G6: =Источники!K6 | H6: =Источники!L6 | I6: =Источники!M6 | J6: =D6-E6-F6-G6-H6+I6
A7: =Валовая!A7 | B7: =Валовая!B7 | C7: =Валовая!C7 | D7: =Валовая!F7 | E7: =Источники!I7 | F7: =Источники!J7 | G7: =Источники!K7 | H7: =Источники!L7 | I7: =Источники!M7 | J7: =D7-E7-F7-G7-H7+I7
A8: =Валовая!A8 | B8: =Валовая!B8 | C8: =Валовая!C8 | D8: =Валовая!F8 | E8: =Источники!I8 | F8: =Источники!J8 | G8: =Источники!K8 | H8: =Источники!L8 | I8: =Источники!M8 | J8: =D8-E8-F8-G8-H8+I8
A9: =Валовая!A9 | B9: =Валовая!B9 | C9: =Валовая!C9 | D9: =Валовая!F9 | E9: =Источники!I9 | F9: =Источники!J9 | G9: =Источники!K9 | H9: =Источники!L9 | I9: =Источники!M9 | J9: =D9-E9-F9-G9-H9+I9
A10: =Валовая!A10 | B10: =Валовая!B10 | C10: =Валовая!C10 | D10: =Валовая!F10 | E10: =Источники!I10 | F10: =Источники!J10 | G10: =Источники!K10 | H10: =Источники!L10 | I10: =Источники!M10 | J10: =D10-E10-F10-G10-H10+I10
A11: =Валовая!A11 | B11: =Валовая!B11 | C11: =Валовая!C11 | D11: =Валовая!F11 | E11: =Источники!I11 | F11: =Источники!J11 | G11: =Источники!K11 | H11: =Источники!L11 | I11: =Источники!M11 | J11: =D11-E11-F11-G11-H11+I11
A12: =Валовая!A12 | B12: =Валовая!B12 | C12: =Валовая!C12 | D12: =Валовая!F12 | E12: =Источники!I12 | F12: =Источники!J12 | G12: =Источники!K12 | H12: =Источники!L12 | I12: =Источники!M12 | J12: =D12-E12-F12-G12-H12+I12
A13: =Валовая!A13 | B13: =Валовая!B13 | C13: =Валовая!C13 | D13: =Валовая!F13 | E13: =Источники!I13 | F13: =Источники!J13 | G13: =Источники!K13 | H13: =Источники!L13 | I13: =Источники!M13 | J13: =D13-E13-F13-G13-H13+I13

Sheet Постоянные
A1: Статья | B1: Сумма, ₽
A2: Зарплата | B2: 2460910.2
A3: Аренда | B3: 820000
A4: IT-услуги | B4: 205000
A5: Прочие услуги | B5: 410000
A6: Прочие административные | B6: 410000
A7: ИТОГО | B7: =SUM(B2:B6)

Sheet Операционная
A1: Категория | B1: Чистая выручка, ₽ | C1: Маржинальная прибыль, ₽ | D1: Доля выручки | E1: Постоянные (alloc), ₽ | F1: Бренд (alloc), ₽ | G1: Транспорт (alloc), ₽ | H1: EBITDA, ₽ | I1: EBITDA, %
A2: Бытхимия | B2: =SUMIFS(Валовая!$D:$D, Валовая!$C:$C, "Бытхимия") | C2: =SUMIFS(Маржинальная!$J:$J, Маржинальная!$C:$C, "Бытхимия") | D2: =B2/SUM($B$2:$B$4) | E2: =D2*Постоянные!$B$7 | F2: =D2*800000 | G2: =D2*510000 | H2: =C2-E2-F2-G2 | I2: =H2/B2
A3: Посуда | B3: =SUMIFS(Валовая!$D:$D, Валовая!$C:$C, "Посуда") | C3: =SUMIFS(Маржинальная!$J:$J, Маржинальная!$C:$C, "Посуда") | D3: =B3/SUM($B$2:$B$4) | E3: =D3*Постоянные!$B$7 | F3: =D3*800000 | G3: =D3*510000 | H3: =C3-E3-F3-G3 | I3: =H3/B3
A4: Стёкла | B4: =SUMIFS(Валовая!$D:$D, Валовая!$C:$C, "Стёкла") | C4: =SUMIFS(Маржинальная!$J:$J, Маржинальная!$C:$C, "Стёкла") | D4: =B4/SUM($B$2:$B$4) | E4: =D4*Постоянные!$B$7 | F4: =D4*800000 | G4: =D4*510000 | H4: =C4-E4-F4-G4 | I4: =H4/B4
A5: ИТОГО | B5: =SUM(B2:B4) | C5: =SUM(C2:C4) | D5: =SUM(D2:D4) | E5: =SUM(E2:E4) | F5: =SUM(F2:F4) | G5: =SUM(G2:G4) | H5: =SUM(H2:H4) | I5: =H5/B5

Sheet Свод
A1: Уровень | B1: Сумма, ₽ | C1: % от чистой выручки
A2: Чистая выручка | B2: =Операционная!B5 | C2: 1
A3: Маржинальная прибыль | B3: =Операционная!C5 | C3: =B3/B$2
A4: (−) Постоянные | B4: =-Операционная!E5 | C4: =B4/B$2
A5: (−) Бренд-маркетинг | B5: =-Операционная!F5 | C5: =B5/B$2
A6: (−) Транспорт | B6: =-Операционная!G5 | C6: =B6/B$2
A7: EBITDA | B7: =Операционная!H5 | C7: =Операционная!I5
